seurvalencia/__init__.py
seurvalencia/api.py
seurvalencia/picking.py
seurvalencia/utils.py
seurvalencia/template/get_city.xml
seurvalencia/template/picking_info.xml
seurvalencia/template/picking_send.xml
seurvalencia/template/validate_user.xml
seurvalencia-0.0.5.dist-info/LICENSE
seurvalencia-0.0.5.dist-info/METADATA
seurvalencia-0.0.5.dist-info/WHEEL
seurvalencia-0.0.5.dist-info/top_level.txt
seurvalencia-0.0.5.dist-info/RECORD
