Metadata-Version: 2.1
Name: seurvalencia
Version: 0.0.5
Summary: Python API Seur Valencia carrier
Home-page: https://www.zikzakmedia.com
Author: Zikzakmedia SL
Author-email: zikzak@zikzakmedia.com
License: GPL-3
Download-URL: https://bitbucket.org/zikzakmedia/python-seurvalencia
Platform: UNKNOWN
Classifier: Development Status :: 4 - Beta
Classifier: Environment :: Web Environment
Classifier: Intended Audience :: Developers
Classifier: License :: OSI Approved :: GNU Affero General Public License v3
Classifier: Operating System :: OS Independent
Classifier: Programming Language :: Python :: 2
Classifier: Programming Language :: Python :: 3
Classifier: Topic :: Internet :: WWW/HTTP :: Dynamic Content
Classifier: Topic :: Software Development :: Libraries :: Python Modules
Requires-Dist: genshi
